mlflow_databricks_artifacts/__init__.py
mlflow_databricks_artifacts/environment_variables.py
mlflow_databricks_artifacts/exceptions.py
mlflow_databricks_artifacts/azure/__init__.py
mlflow_databricks_artifacts/azure/client.py
mlflow_databricks_artifacts/protos/__init__.py
mlflow_databricks_artifacts/protos/patched_databricks_artifacts_pb2.py
mlflow_databricks_artifacts/protos/scalapb/__init__.py
mlflow_databricks_artifacts/store/__init__.py
mlflow_databricks_artifacts/store/artifact_repo.py
mlflow_databricks_artifacts/store/entrypoint.py
mlflow_databricks_artifacts/store/db/__init__.py
mlflow_databricks_artifacts/store/db/db_types.py
mlflow_databricks_artifacts/tests/__init__.py
mlflow_databricks_artifacts/tests/test_repo.py
mlflow_databricks_artifacts/tracking/__init__.py
mlflow_databricks_artifacts/tracking/request_header/__init__.py
mlflow_databricks_artifacts/tracking/request_header/abstract_request_header_provider.py
mlflow_databricks_artifacts/tracking/request_header/databricks_request_header_provider.py
mlflow_databricks_artifacts/tracking/request_header/default_request_header_provider.py
mlflow_databricks_artifacts/tracking/request_header/registry.py
mlflow_databricks_artifacts/utils/__init__.py
mlflow_databricks_artifacts/utils/_spark_utils.py
mlflow_databricks_artifacts/utils/databricks_utils.py
mlflow_databricks_artifacts/utils/file_utils.py
mlflow_databricks_artifacts/utils/process.py
mlflow_databricks_artifacts/utils/proto_json_utils.py
mlflow_databricks_artifacts/utils/rest_utils.py
mlflow_databricks_artifacts/utils/string_utils.py
mlflow_databricks_artifacts/utils/uri.py
mlflow_databricks_artifacts-2.0.1.dist-info/METADATA
mlflow_databricks_artifacts-2.0.1.dist-info/WHEEL
mlflow_databricks_artifacts-2.0.1.dist-info/entry_points.txt
mlflow_databricks_artifacts-2.0.1.dist-info/top_level.txt
mlflow_databricks_artifacts-2.0.1.dist-info/RECORD
