Metadata-Version: 2.1
Name: mlflow-databricks-artifacts
Version: 2.0.1
Summary: Plugin to create and access MLflow-managed artifacts on Databricks
Author: Databricks
Requires-Dist: mlflow-skinny (>1.10.0)
